pytus/__init__.py
pytus/main.py
pytus-0.2.1.dist-info/LICENSE
pytus-0.2.1.dist-info/WHEEL
pytus-0.2.1.dist-info/METADATA
pytus-0.2.1.dist-info/RECORD
